djangocms_4_migration/__init__.py
djangocms_4_migration/admin.py
djangocms_4_migration/apps.py
djangocms_4_migration/helpers.py
djangocms_4_migration/models.py
djangocms_4_migration/tests.py
djangocms_4_migration/views.py
djangocms_4_migration/management/__init__.py
djangocms_4_migration/management/commands/__init__.py
djangocms_4_migration/management/commands/cms4_migration.py
djangocms_4_migration/management/commands/migrate_alias_plugins.py
djangocms_4_migration/management/commands/migrate_static_placeholders.py
djangocms_4_migration/management/commands/migration_cleanup.py
djangocms_4_migration/management/commands/migration_preparation.py
djangocms_4_migration/management/commands/remove_unlinked_placeholders.py
djangocms_4_migration/migrations/0001_initial.py
djangocms_4_migration/migrations/0002_collect_removed_data_data_migration.py
djangocms_4_migration/migrations/0003_page_version_integration_data_migration.py
djangocms_4_migration/migrations/__init__.py
djangocms_4_migration-0.0.2.dist-info/LICENSE
djangocms_4_migration-0.0.2.dist-info/METADATA
djangocms_4_migration-0.0.2.dist-info/WHEEL
djangocms_4_migration-0.0.2.dist-info/top_level.txt
djangocms_4_migration-0.0.2.dist-info/RECORD
