Metadata-Version: 2.1
Name: djangocms-4-migration
Version: 0.0.2
Summary: A django CMS 3 to 4 migration package
Home-page: https://github.com/Aiky30/djangocms-4-migration/
Author: Andrew Aikman (Aiky30)
Classifier: Programming Language :: Python :: 3
Classifier: License :: OSI Approved :: BSD License
Classifier: Operating System :: OS Independent
License-File: LICENSE
